enzu/__init__.py
enzu/api.py
enzu/bench.py
enzu/budget.py
enzu/cli.py
enzu/client.py
enzu/contract.py
enzu/doctor.py
enzu/engine.py
enzu/exceptions.py
enzu/jobs.py
enzu/models.py
enzu/openresponses.py
enzu/py.typed
enzu/queue.py
enzu/retry.py
enzu/schema.py
enzu/security.py
enzu/server.py
enzu/session.py
enzu/telemetry.py
enzu/terminology.py
enzu/usage.py
enzu/isolation/__init__.py
enzu/isolation/audit.py
enzu/isolation/concurrency.py
enzu/isolation/container.py
enzu/isolation/container_wrapper.py
enzu/isolation/health.py
enzu/isolation/ipc.py
enzu/isolation/metrics.py
enzu/isolation/pool.py
enzu/isolation/runner.py
enzu/isolation/runtime.py
enzu/isolation/scheduler.py
enzu/metrics/__init__.py
enzu/metrics/collector.py
enzu/metrics/run_event.py
enzu/providers/__init__.py
enzu/providers/base.py
enzu/providers/openai_compat.py
enzu/providers/pool.py
enzu/providers/registry.py
enzu/providers/resolve.py
enzu/repl/__init__.py
enzu/repl/protocol.py
enzu/repl/safe.py
enzu/repl/sandbox.py
enzu/retries/__init__.py
enzu/retries/tracking.py
enzu/rlm/__init__.py
enzu/rlm/budget.py
enzu/rlm/context_metrics.py
enzu/rlm/engine.py
enzu/rlm/feedback.py
enzu/rlm/llm_executor.py
enzu/rlm/prompts.py
enzu/rlm/runner.py
enzu/rlm/sandbox_factory.py
enzu/rlm/verification.py
enzu/runtime/__init__.py
enzu/runtime/distributed.py
enzu/runtime/local.py
enzu/runtime/protocol.py
enzu/runtime/worker.py
enzu/sandbox/__init__.py
enzu/sandbox/image.py
enzu/sandbox/lifecycle.py
enzu/server/__init__.py
enzu/server/app.py
enzu/server/auth.py
enzu/server/config.py
enzu/server/exceptions.py
enzu/server/middleware.py
enzu/server/schemas.py
enzu/server/routers/__init__.py
enzu/server/routers/health.py
enzu/server/routers/run.py
enzu/server/routers/sessions.py
enzu/server/routers/tasks.py
enzu/server/services/__init__.py
enzu/server/services/enzu_service.py
enzu/server/services/session_manager.py
enzu/spec/__init__.py
enzu/spec/openresponses_openapi.json
enzu/stress/__init__.py
enzu/stress/faults.py
enzu-0.3.0.dist-info/licenses/LICENSE
enzu-0.3.0.dist-info/METADATA
enzu-0.3.0.dist-info/WHEEL
enzu-0.3.0.dist-info/entry_points.txt
enzu-0.3.0.dist-info/top_level.txt
enzu-0.3.0.dist-info/RECORD
