Metadata-Version: 2.4
Name: enzu
Version: 0.3.0
Summary: Budgeted LLM task orchestration with hard limits and long-context RLM.
Author: teilomillet
License: Apache-2.0
Project-URL: Homepage, https://github.com/teilomillet/enzu
Project-URL: Repository, https://github.com/teilomillet/enzu
Project-URL: Documentation, https://github.com/teilomillet/enzu/tree/main/docs
Project-URL: Issues, https://github.com/teilomillet/enzu/issues
Project-URL: Changelog, https://github.com/teilomillet/enzu/blob/main/CHANGELOG.md
Keywords: llm,ai,orchestration,budget,rlm,agents,workflow,openai,anthropic,openrouter
Classifier: Development Status :: 4 - Beta
Classifier: Intended Audience :: Developers
Classifier: License :: OSI Approved :: Apache Software License
Classifier: Programming Language :: Python :: 3
Classifier: Programming Language :: Python :: 3.9
Classifier: Programming Language :: Python :: 3.10
Classifier: Programming Language :: Python :: 3.11
Classifier: Programming Language :: Python :: 3.12
Classifier: Programming Language :: Python :: 3.13
Classifier: Topic :: Scientific/Engineering :: Artificial Intelligence
Classifier: Typing :: Typed
Requires-Python: >=3.9
License-File: LICENSE
Requires-Dist: openai>=1.0.0
Requires-Dist: pydantic>=2.0.0
Requires-Dist: pypdf>=4.0.0
Requires-Dist: python-dotenv>=1.0.0
Requires-Dist: httpx>=0.25.0
Requires-Dist: logfire>=4.19.0
Requires-Dist: tiktoken>=0.5.0
Provides-Extra: dev
Requires-Dist: pytest>=7.0.0; extra == "dev"
Requires-Dist: pytest-cov>=4.0.0; extra == "dev"
Requires-Dist: pytest-asyncio>=0.23.0; extra == "dev"
Requires-Dist: pytest-xdist>=3.6.0; extra == "dev"
Requires-Dist: ruff>=0.4.0; extra == "dev"
Requires-Dist: ty>=0.0.14; extra == "dev"
Provides-Extra: telemetry
Requires-Dist: logfire; extra == "telemetry"
Provides-Extra: server
Requires-Dist: fastapi>=0.111.0; extra == "server"
Requires-Dist: uvicorn[standard]>=0.30.0; extra == "server"
Provides-Extra: docling
Requires-Dist: docling>=2.0.0; extra == "docling"
Provides-Extra: all
Requires-Dist: enzu[dev]; extra == "all"
Requires-Dist: enzu[telemetry]; extra == "all"
Requires-Dist: enzu[server]; extra == "all"
Requires-Dist: enzu[docling]; extra == "all"
Dynamic: license-file
